LICENSE
MANIFEST.in
README.md
requirements.txt
setup.cfg
setup.py
s3_encryption/VERSION
s3_encryption/__init__.py
s3_encryption/__init__.pyc
s3_encryption/client.py
s3_encryption/crypto.py
s3_encryption/crypto.pyc
s3_encryption/envelope.py
s3_encryption/envelope.pyc
s3_encryption/exceptions.py
s3_encryption/exceptions.pyc
s3_encryption/handler.py
s3_encryption/handler.pyc
s3_encryption/key_provider.py
s3_encryption/materials.py
s3_encryption.egg-info/PKG-INFO
s3_encryption.egg-info/SOURCES.txt
s3_encryption.egg-info/dependency_links.txt
s3_encryption.egg-info/not-zip-safe
s3_encryption.egg-info/requires.txt
s3_encryption.egg-info/top_level.txt