Metadata-Version: 1.1
Name: s3-encryption
Version: 0.1.2
Summary: Thin wrapper around boto3 S3 client which supports client side encryption compatable with ruby aws-sdk-core
Home-page: https://github.com/boldfield/s3-encryption
Author: Brian Oldfield
Author-email: brian@oldfield.io
License: BSD
Download-URL: https://github.com/boldfield/s3-encryption/tarball/0.1.2
Keywords: S3 encryption
Platform: UNKNOWN
Classifier: Development Status :: 4 - Beta
Classifier: Intended Audience :: Developers
